halper/__init__.py
halper/constants.py
halper/default_config.toml
halper/halp.py
halper/cli/__init__.py
halper/cli/config.py
halper/cli/helpers.py
halper/cli/hide.py
halper/cli/index.py
halper/cli/list.py
halper/cli/search.py
halper/cli/unhide.py
halper/controllers/__init__.py
halper/controllers/db_queries.py
halper/controllers/indexer.py
halper/models/__init__.py
halper/models/category.py
halper/models/command.py
halper/models/file.py
halper/models/index_result.py
halper/models/parser.py
halper/models/user_defined_category.py
halper/utils/__init__.py
halper/utils/config.py
halper/utils/database.py
halper/utils/errors.py
halper/utils/mankier.py
halper/utils/printer.py
halper/utils/text_parsers.py
halper/utils/utilities.py
halper/views/__init__.py
halper/views/commands.py
halper/views/indexer.py
halper/views/list.py
halper-2.0.2.dist-info/METADATA
halper-2.0.2.dist-info/WHEEL
halper-2.0.2.dist-info/entry_points.txt
halper-2.0.2.dist-info/licenses/LICENSE
halper-2.0.2.dist-info/RECORD
