Metadata-Version: 2.4
Name: halper
Version: 2.0.2
Summary: One stop shop for command line help.
Project-URL: Homepage, https://github.com/natelandau/halp
Project-URL: Repository, https://github.com/natelandau/halp
Author-email: Nate Landau <github@natenate.org>
License:                     GNU AFFERO GENERAL PUBLIC LICENSE
License-File: LICENSE
Requires-Python: >=3.11
Requires-Dist: cappa>=0.26.6
Requires-Dist: dynaconf>=3.2.10
Requires-Dist: httpx>=0.28.1
Requires-Dist: inflect>=7.5.0
Requires-Dist: markdownify>=1.1.0
Requires-Dist: parsy>=2.1
Requires-Dist: peewee>=3.17.9
Requires-Dist: rich>=13.9.4
Requires-Dist: semver>=3.0.4
Requires-Dist: sh>=2.2.2
